chatnoir_api/__init__.py
chatnoir_api/cache.py
chatnoir_api/constants.py
chatnoir_api/defaults.py
chatnoir_api/lazy.py
chatnoir_api/logger.py
chatnoir_api/py.typed
chatnoir_api/model/__init__.py
chatnoir_api/model/highlight.py
chatnoir_api/model/result.py
chatnoir_api/v1/__init__.py
chatnoir_api/v1/model.py
chatnoir_api/v1/requests.py
chatnoir_api/v1/search.py
chatnoir_api/v1/search_phrases.py
chatnoir_api-3.4.2.dist-info/licenses/LICENSE
examples/__init__.py
examples/cache.py
examples/chat.py
examples/search.py
examples/search_iterator.py
examples/search_page.py
examples/search_single.py
tests/__init__.py
tests/conftest.py
tests/test_cache.py
tests/test_highlight.py
tests/test_model.py
tests/test_search.py
tests/test_search_methods.py
tests/test_search_phrases.py
tests/test_term_vectors.py
chatnoir_api-3.4.2.dist-info/METADATA
chatnoir_api-3.4.2.dist-info/WHEEL
chatnoir_api-3.4.2.dist-info/top_level.txt
chatnoir_api-3.4.2.dist-info/RECORD
