Metadata-Version: 2.4
Name: chatnoir-api
Version: 3.4.2
Summary: Simple, type-safe access to the ChatNoir search API.
Author-email: Jan Heinrich Merker <heinrich.merker@uni-jena.de>, Maik Fröbe <maik.froebe@uni-jena.de>
Project-URL: Homepage, https://github.com/chatnoir-eu/chatnoir-api
Project-URL: Bug Tracker, https://github.com/chatnoir-eu/chatnoir-api/issues
Classifier: Programming Language :: Python :: 3
Classifier: Programming Language :: Python :: 3 :: Only
Classifier: Programming Language :: Python :: 3.8
Classifier: Programming Language :: Python :: 3.9
Classifier: Programming Language :: Python :: 3.10
Classifier: Programming Language :: Python :: 3.11
Classifier: Programming Language :: Python :: 3.12
Classifier: License :: OSI Approved :: MIT License
Classifier: Operating System :: OS Independent
Classifier: Intended Audience :: Science/Research
Classifier: Topic :: Scientific/Engineering
Requires-Python: >=3.8
License-File: LICENSE
Requires-Dist: requests~=2.32
Requires-Dist: pydantic~=2.10
Requires-Dist: typing-extensions~=4.12
Requires-Dist: importlib-metadata~=8.5
Requires-Dist: websocket-client~=1.8
Provides-Extra: tests
Requires-Dist: bandit[toml]~=1.7; extra == "tests"
Requires-Dist: mypy~=1.13; extra == "tests"
Requires-Dist: pytest~=8.3; extra == "tests"
Requires-Dist: pytest-cov<8,>=5; extra == "tests"
Requires-Dist: ruff<0.14.0,>=0.7.1; extra == "tests"
Requires-Dist: types-requests~=2.32; extra == "tests"
Dynamic: license-file
